{
  "brand": {
    "logo": "Jason Analytics"
  },
  "nav": {
    "home": "Home",
    "services": "Services",
    "portfolio": "Portfolio",
    "dashboards": "Dashboards",
    "reports": "💎 Premium",
    "articles": "Articles",
    "experience": "Exp.",
    "contact": "Contact"
  },
  "home": {
    "title": "Translating Complex Data into Intuitive Decisions",
    "subtitle": "I'm Jason Tsai, Your Dedicated Data Analyst",
    "description": "Offering deep cross-disciplinary expertise. I am more than a Data Analyst—I provide comprehensive services in [Data Analysis], [Business Analytics], [Project Teaching], [Technical Enablement], and [Professional Consulting] to uncover the highest commercial value from vast amounts of data.",
    "cta": "Explore Projects",
    "contact_cta": "Discuss Cooperation",
    "featured_courses": "Featured Courses",
    "social_label": "Follow my Data Insights",
    "featured_highlights": "Featured Highlights",
    "stats": {
      "students": "Students",
      "projects": "Guided Projects",
      "hours": "Online Course Hours"
    }
  }
}
